genetics/__init__.py
genetics/genetics.py
genetics-1.0.0.dist-info/DESCRIPTION.rst
genetics-1.0.0.dist-info/METADATA
genetics-1.0.0.dist-info/RECORD
genetics-1.0.0.dist-info/WHEEL
genetics-1.0.0.dist-info/metadata.json
genetics-1.0.0.dist-info/top_level.txt
