Metadata-Version: 2.0
Name: genetics
Version: 1.0.0
Summary: Genetic Algorithm in Python, which could be used for Sampling, Feature Select, Model Select, etc in Machine Learning
Home-page: https://github.com/Marcnuth/genetics
Author: Marcnuth
Author-email: marcnuth@foxmail.com
License: Apache License 2.0
Keywords: genetic-algorithm,machine-learning,sampling,feature-engineering,model-selection
Platform: UNKNOWN
Classifier: Development Status :: 4 - Beta
Classifier: Intended Audience :: Developers
Classifier: License :: OSI Approved :: Apache Software License
Classifier: Topic :: Scientific/Engineering :: Artificial Intelligence
Classifier: Topic :: Software Development :: Libraries
Classifier: Programming Language :: Python :: 3
Requires-Dist: numpy
